tomlpatch/__init__.py
tomlpatch/logger.py
tomlpatch/main.py
tomlpatch-0.2.0.dist-info/entry_points.txt
tomlpatch-0.2.0.dist-info/LICENSE
tomlpatch-0.2.0.dist-info/WHEEL
tomlpatch-0.2.0.dist-info/METADATA
tomlpatch-0.2.0.dist-info/RECORD
