Metadata-Version: 2.1
Name: tomlpatch
Version: 0.2.0
Summary: 
Author: Yue Ni
Author-email: niyue.com@gmail.com
Requires-Python: >=3.10,<4.0
Classifier: Programming Language :: Python :: 3
Classifier: Programming Language :: Python :: 3.10
Classifier: Programming Language :: Python :: 3.11
Requires-Dist: dotty-dict (>=1.3.1,<2.0.0)
Requires-Dist: tomli (>=2.0.1,<3.0.0)
Requires-Dist: tomli-w (>=1.0.0,<2.0.0)
